cml_wd_pytorch/__init__.py
cml_wd_pytorch/config/config.yml
cml_wd_pytorch/dataloader/__init__.py
cml_wd_pytorch/dataloader/dataloaderzarr.py
cml_wd_pytorch/evaluation/__init__.py
cml_wd_pytorch/evaluation/summarize_scores.py
cml_wd_pytorch/evaluation/summarize_scores_wet_dry.py
cml_wd_pytorch/inference/__init__.py
cml_wd_pytorch/inference/run_inference.py
cml_wd_pytorch/models/__init__.py
cml_wd_pytorch/models/cnn.py
cml_wd_pytorch/train/__init__.py
cml_wd_pytorch/train/training_rain_rate.py
cml_wd_pytorch/train/training_wet_dry.py
cml_wd_pytorch-0.1.4.dist-info/METADATA
cml_wd_pytorch-0.1.4.dist-info/WHEEL
cml_wd_pytorch-0.1.4.dist-info/entry_points.txt
cml_wd_pytorch-0.1.4.dist-info/licenses/LICENSE
cml_wd_pytorch-0.1.4.dist-info/RECORD
