Metadata-Version: 2.4
Name: cml-wd-pytorch
Version: 0.1.4
Summary: Add your description here
Author-email: "julius.polz" <julius.polz@kit.edu>
License-File: LICENSE
Requires-Python: >=3.9
Requires-Dist: dask
Requires-Dist: einops
Requires-Dist: ipykernel
Requires-Dist: matplotlib
Requires-Dist: netcdf4
Requires-Dist: pyyaml
Requires-Dist: scikit-learn
Requires-Dist: torch
Requires-Dist: torchinfo
Requires-Dist: tqdm
Requires-Dist: xarray
Requires-Dist: zarr~=2.17
